LICENSE
MANIFEST.in
README.rst
setup.py
django_googlemap.egg-info/PKG-INFO
django_googlemap.egg-info/SOURCES.txt
django_googlemap.egg-info/dependency_links.txt
django_googlemap.egg-info/not-zip-safe
django_googlemap.egg-info/top_level.txt
googlemap/__init__.py
googlemap/models.py
googlemap/settings.py
googlemap/urls.py
googlemap/utils.py
googlemap/views.py
googlemap/data/GeoLiteCity.dat
googlemap/ip2geo/__init__.py
googlemap/ip2geo/__init__.pyc
googlemap/ip2geo/const.py
googlemap/ip2geo/const.pyc
googlemap/ip2geo/timezone.py
googlemap/ip2geo/timezone.pyc
googlemap/ip2geo/util.py
googlemap/ip2geo/util.pyc
googlemap/static/img/marker_blackCircle.png
googlemap/static/img/marker_circle.png
googlemap/static/img/marker_green.png
googlemap/static/img/marker_redCircle.png
googlemap/static/js/gmap.js
googlemap/templates/gmap/ip_on_map.html
googlemap/templatetags/__init__.py
googlemap/templatetags/__init__.pyc
googlemap/templatetags/gmap_tags.py
googlemap/templatetags/gmap_tags.pyc