Metadata-Version: 1.1
Name: django-googlemap
Version: 0.5
Summary: django-googlemap is a simple Django app to show the google map from ip addresses.
Home-page: https://github.com/mygu/django-googlemap
Author: Mingyu Gu
Author-email: mingyugu0410@gmail.com
License: BSD License
Platform: UNKNOWN
Classifier: Environment :: Web Environment
Classifier: Framework :: Django
Classifier: Intended Audience :: Developers
Classifier: License :: OSI Approved :: BSD License
Classifier: Operating System :: OS Independent
Classifier: Programming Language :: Python
Classifier: Programming Language :: Python :: 3
Classifier: Programming Language :: Python :: 3.2
Classifier: Programming Language :: Python :: 3.3
Classifier: Topic :: Internet :: WWW/HTTP
Classifier: Topic :: Internet :: WWW/HTTP :: Dynamic Content
